LICENSE
MANIFEST.in
README.md
pyproject.toml
setup.py
docs/gen_ref_pages.py
docs/assets/logo.png
docs/assets/readme_demo.png
jaxquantum/PACKAGE.json
jaxquantum/__init__.py
jaxquantum.egg-info/PKG-INFO
jaxquantum.egg-info/SOURCES.txt
jaxquantum.egg-info/dependency_links.txt
jaxquantum.egg-info/requires.txt
jaxquantum.egg-info/top_level.txt
jaxquantum/circuits/__init__.py
jaxquantum/circuits/circuits.py
jaxquantum/circuits/constants.py
jaxquantum/circuits/gates.py
jaxquantum/circuits/simulate.py
jaxquantum/circuits/library/__init__.py
jaxquantum/circuits/library/generic.py
jaxquantum/circuits/library/oscillator.py
jaxquantum/circuits/library/qubit.py
jaxquantum/codes/__init__.py
jaxquantum/codes/base.py
jaxquantum/codes/binomial.py
jaxquantum/codes/cat.py
jaxquantum/codes/gkp.py
jaxquantum/codes/mode.py
jaxquantum/codes/qubit.py
jaxquantum/core/__init__.py
jaxquantum/core/cfunctions.py
jaxquantum/core/conversions.py
jaxquantum/core/dims.py
jaxquantum/core/measurements.py
jaxquantum/core/operators.py
jaxquantum/core/qarray.py
jaxquantum/core/qp_distributions.py
jaxquantum/core/settings.py
jaxquantum/core/solvers.py
jaxquantum/core/visualization.py
jaxquantum/devices/__init__.py
jaxquantum/devices/analysis/__init__.py
jaxquantum/devices/analysis/sweeps.py
jaxquantum/devices/base/__init__.py
jaxquantum/devices/base/base.py
jaxquantum/devices/base/system.py
jaxquantum/devices/common/__init__.py
jaxquantum/devices/common/utils.py
jaxquantum/devices/superconducting/__init__.py
jaxquantum/devices/superconducting/ats.py
jaxquantum/devices/superconducting/drive.py
jaxquantum/devices/superconducting/flux_base.py
jaxquantum/devices/superconducting/fluxonium.py
jaxquantum/devices/superconducting/ideal_qubit.py
jaxquantum/devices/superconducting/kno.py
jaxquantum/devices/superconducting/resonator.py
jaxquantum/devices/superconducting/snail.py
jaxquantum/devices/superconducting/transmon.py
jaxquantum/devices/superconducting/tunable_transmon.py
jaxquantum/utils/__init__.py
jaxquantum/utils/utils.py
test/test_circuits.py
test/test_codes.py
test/test_core_misc.py
test/test_core_solvers.py
test/test_measurement.py
test/test_qarray.py
