Metadata-Version: 2.1
Name: jaxquantum
Version: 0.2.2
Summary: jaxquantum
Home-page: https://jaxquantum.org
Author: Shantanu Jha, Shoumik Chowdhury, Gabriele Rolleri, Max Hays
Author-email: shantanu.rajesh.jha@gmail.com
License: Apache-2.0
Project-URL: Documentation, https://jaxquantum.org
Project-URL: Source Code, https://github.com/EQuS/jaxquantum
Project-URL: Tutorials, https://github.com/EQuS/jaxquantum/tree/main/tutorials
Keywords: quantum computing
Classifier: Environment :: Console
Classifier: Intended Audience :: Developers
Classifier: Intended Audience :: Science/Research
Classifier: Operating System :: Microsoft :: Windows
Classifier: Operating System :: MacOS :: MacOS X
Classifier: Operating System :: POSIX :: Linux
Classifier: Programming Language :: Python :: 3 :: Only
Classifier: Topic :: Scientific/Engineering
Requires-Python: >=3.7
License-File: LICENSE
Requires-Dist: numpy
Requires-Dist: matplotlib
Requires-Dist: qutip
Requires-Dist: jax[cpu]
Requires-Dist: diffrax
Requires-Dist: flax
Requires-Dist: tqdm
Requires-Dist: optax
Requires-Dist: jax-tqdm
Provides-Extra: dev
Requires-Dist: jupyterlab>=3.1.0; extra == "dev"
Requires-Dist: mypy; extra == "dev"
Requires-Dist: pylint; extra == "dev"
Requires-Dist: black; extra == "dev"
Requires-Dist: coverage; extra == "dev"
Provides-Extra: docs
Requires-Dist: mkdocs; extra == "docs"
Requires-Dist: mkdocs-material; extra == "docs"
Requires-Dist: mkdocs-literate-nav; extra == "docs"
Requires-Dist: mkdocs-section-index; extra == "docs"
Requires-Dist: mkdocs-gen-files; extra == "docs"
Requires-Dist: mkdocstrings-python; extra == "docs"
Requires-Dist: mkdocs-jupyter; extra == "docs"
Requires-Dist: pymdown-extensions; extra == "docs"
Provides-Extra: tests
Requires-Dist: pytest; extra == "tests"
Requires-Dist: pytest-cov; extra == "tests"
Provides-Extra: gpu
Requires-Dist: jax[cuda12]; extra == "gpu"
Provides-Extra: tpu
Requires-Dist: jax[tpu]; extra == "tpu"
